CHANGES.rst
COPYING
MANIFEST.in
Makefile
README.rst
bootstrap-buildout.py
buildout.cfg
ez_setup.py
requirements-dev.in
requirements-dev.txt
setup.cfg
setup.py
tox.ini
docs/Makefile
docs/make.bat
docs/source/conf.py
docs/source/index.rst
rrn_kr/__init__.py
rrn_kr/__main__.py
rrn_kr/cli.py
rrn_kr/colander.py
rrn_kr/core.py
rrn_kr/wsgi.py
rrn_kr.egg-info/PKG-INFO
rrn_kr.egg-info/SOURCES.txt
rrn_kr.egg-info/dependency_links.txt
rrn_kr.egg-info/entry_points.txt
rrn_kr.egg-info/not-zip-safe
rrn_kr.egg-info/requires.txt
rrn_kr.egg-info/top_level.txt
rrn_kr/locale/rrn_kr.pot
rrn_kr/locale/en/LC_MESSAGES/rrn_kr.po
rrn_kr/locale/ko/LC_MESSAGES/rrn_kr.po
rrn_kr/recipe/__init__.py
rrn_kr/tests/__init__.py
rrn_kr/tests/test_app.py
rrn_kr/tests/test_colander.py
rrn_kr/tests/test_core.py